serpent_lang-0.1.1.dist-info/METADATA
serpent_lang-0.1.1.dist-info/WHEEL
serpent_lang/__init__.py
serpent_lang/agents/__init__.py
serpent_lang/agents/base_agent.py
serpent_lang/agents/base_react_agent.py
serpent_lang/chains/__init__.py
serpent_lang/chains/base_chain.py
serpent_lang/chains/base_chat_chain.py
serpent_lang/chains/base_message_chain.py
serpent_lang/chains/base_rag_chain.py
serpent_lang/configuration/__init__.py
serpent_lang/configuration/settings.py
serpent_lang/core/__init__.py
serpent_lang/core/base_chat_model_action.py
serpent_lang/cosmos_vcore_retriever.py
serpent_lang/graphs/__init__.py
serpent_lang/graphs/agent_node.py
serpent_lang/graphs/base_graph_engine.py
serpent_lang/models/__init__.py
serpent_lang/models/extensions.py
serpent_lang/models/llm_factory.py
serpent_lang/models/model_settings.py
serpent_lang/tools/__init__.py
serpent_lang/tools/base_retrievers.py
serpent_lang/tools/base_tools.py
serpent_lang/util/__init__.py
serpent_lang/util/memory_cache.py
serpent_lang-0.1.1.dist-info/RECORD
