Metadata-Version: 2.1
Name: serpent-lang
Version: 0.1.1
Summary: Helpful tools for querying and managing data in a natural language format.
Author-Email: Brian Aiken <bpaiken570@gmail.com>
License: MIT
Requires-Python: <3.12,>=3.10
Requires-Dist: cachetools>=5.4.0
Requires-Dist: pydantic>=2.8.2
Requires-Dist: langchain>=0.2.12
Requires-Dist: pymongo>=4.8.0
Requires-Dist: langchain-openai>=0.1.20
Requires-Dist: langgraph>=0.1.19
Requires-Dist: pytz>=2024.1
Requires-Dist: rapidfuzz>=3.9.5
Requires-Dist: pydantic-settings>=2.4.0
Requires-Dist: langchain-community==0.2.10
